{
    "Result": true, 
    "Message": "123", 
    "Data": {
        "VehicleLicense": {
            "Address": null, 
            "EngineNo": null, 
            "IssueDate": null, 
            "Model": null, 
            "Owner": null, 
            "PlateNo": null, 
            "RegisterDate": null, 
            "UseCharacter": null, 
            "VIN": "LSVHJ133022221761", 
            "VehicleType": null
        }, 
        "StyleList": [
            {
                "MakeId": "8", 
                "MakeName": "大众", 
                "ModelId": "1801", 
                "ModelName": "桑塔纳2000", 
                "StyleId": "6319", 
                "StyleName": "1.8L 自动 GSI时代阳光", 
                "StyleYear": "2003", 
                "Emission": "1.8", 
                "EnvironmentStandard": "国2"
            },{
                "MakeId": "8", 
                "MakeName": "大众", 
                "ModelId": "1801", 
                "ModelName": "桑塔纳2000", 
                "StyleId": "6319", 
                "StyleName": "1.8L 自动 GSI时代阳光", 
                "StyleYear": "2003", 
                "Emission": "1.8", 
                "EnvironmentStandard": "国2"
            },{
                "MakeId": "8", 
                "MakeName": "大众", 
                "ModelId": "1801", 
                "ModelName": "桑塔纳2000", 
                "StyleId": "6319", 
                "StyleName": "1.8L 自动 GSI时代阳光", 
                "StyleYear": "2003", 
                "Emission": "1.8", 
                "EnvironmentStandard": "国2"
            },{
                "MakeId": "8", 
                "MakeName": "大众", 
                "ModelId": "1801", 
                "ModelName": "桑塔纳2000", 
                "StyleId": "6319", 
                "StyleName": "1.8L 自动 GSI时代阳光", 
                "StyleYear": "2003", 
                "Emission": "1.8", 
                "EnvironmentStandard": "国2"
            },{
                "MakeId": "8", 
                "MakeName": "大众", 
                "ModelId": "1801", 
                "ModelName": "桑塔纳2000", 
                "StyleId": "6319", 
                "StyleName": "1.8L 自动 GSI时代阳光", 
                "StyleYear": "2003", 
                "Emission": "1.8", 
                "EnvironmentStandard": "国2"
            }
        ]
    }, 
    "RowCount": 0
}

