{
	"Result": true,
	"Message": "",
	"Data": {
		"CarName": "奥迪a4 12 123 1231",
		"CarPriceText": "17.98",
		"LincenseYear": 2015,
		"LicenseMonth": 3,
		"Mileage": 2,
		"CityName": "北京",
		"ApplyAmount": 0,
		"LoanAmount": 1.5920,
		"B2CCarValuation": 1.4,
		"CarEstimate": {
			"A": "2.14",
			"B": "1.99",
			"C": "1.74"
		},
		"ScrapValue": [{
			"Year": "2018",
			"Price": "1.02"
		}, {
			"Year": "2019",
			"Price": "0.82"
		}, {
			"Year": "2020",
			"Price": "0.66"
		}]
	},
	"RowCount": 0
}