{"Result":true,"Message":"成功","ProductDownpaymentrates":[{"ProductID":142480,"DownPaymentRate":0,"RepaymentPeriod":36,"SecurityDepositRate":0.05,"HasProduct":true,"HasOtherProduct":true,"IsFitForFinance":true}],"ProductRepaymentperiods":[{"ProductID":142480,"DownPaymentRate":0,"RepaymentPeriod":36,"SecurityDepositRate":0.05,"HasProduct":true,"HasOtherProduct":true,"IsFitForFinance":true}],"ProductSecurityDepositRates":[{"ProductID":142480,"DownPaymentRate":0,"RepaymentPeriod":36,"SecurityDepositRate":0.05,"HasProduct":true,"HasOtherProduct":true,"IsFitForFinance":true}]}